{
    "davglass": {
        "name": "Dav Glass",
        "title": "Chair, Founder",
        "org": "Principal Engineer, MedicAlert Foundation",
        "twitter": "davglass"
    },
    "jacob": {
        "name": "Jacob Morton",
        "title": "Vice-Chair, Founder",
        "org": "Engineer, MedicAlert Foundation",
        "twitter": "mkoopajr"
    },
    "bonnie": {
        "name": "Bonnie Kucharski",
        "title": "Treasurer",
        "org": "Community Business Leader"
    },
    "lynn": {
        "name": "Lynn Andersen Lindberg",
        "title": "Secretary",
        "org": "Director, Business Innovation and Research, SIU Research Park",
        "twitter": "SIUSBDC"
    },
    "andrew": {
        "name": "Andrew Wilson",
        "title": "Director",
        "org": "Assistant State's Attorney in Williamson County",
        "twitter": "wilsonian8"
    }
}
